tap_bronto
