Metadata-Version: 1.1
Name: tap-bronto
Version: 0.0.5
Summary: Singer.io tap for extracting data from the Bronto API
Home-page: https://singer.io
Author: Stitch
Author-email: UNKNOWN
License: UNKNOWN
Platform: UNKNOWN
Classifier: Programming Language :: Python :: 3 :: Only
